pipeline_scheduler/__init__.py
pipeline_scheduler/__version__.py
pipeline_scheduler/handler.py
pipeline_scheduler/version.py
amphi/pipeline-scheduler/build_log.json
amphi/pipeline-scheduler/package.json
amphi/pipeline-scheduler/static/lib_index_js.8565f7561787e2b97e4f.js
amphi/pipeline-scheduler/static/lib_index_js.8565f7561787e2b97e4f.js.map
amphi/pipeline-scheduler/static/node_modules_dayjs_dayjs_min_js.8695b1ea75517ad6c633.js
amphi/pipeline-scheduler/static/node_modules_dayjs_dayjs_min_js.8695b1ea75517ad6c633.js.map
amphi/pipeline-scheduler/static/remoteEntry.fd16df6014ceb6b29a95.js
amphi/pipeline-scheduler/static/remoteEntry.fd16df6014ceb6b29a95.js.map
amphi/pipeline-scheduler/static/style.js
amphi/pipeline-scheduler/static/style_index_js.8602888d614bf802b30a.js
amphi/pipeline-scheduler/static/style_index_js.8602888d614bf802b30a.js.map
amphi/pipeline-scheduler/static/vendors-node_modules_ant-design_cssinjs_es_index_js.0a106cdc14574efa78bd.js
amphi/pipeline-scheduler/static/vendors-node_modules_ant-design_cssinjs_es_index_js.0a106cdc14574efa78bd.js.map
amphi/pipeline-scheduler/static/vendors-node_modules_ant-design_icons-svg_es_asn_BarsOutlined_js-node_modules_ant-design_icon-ac19c4.2f82d552f6009cfb45f4.js
amphi/pipeline-scheduler/static/vendors-node_modules_ant-design_icons-svg_es_asn_BarsOutlined_js-node_modules_ant-design_icon-ac19c4.2f82d552f6009cfb45f4.js.map
amphi/pipeline-scheduler/static/vendors-node_modules_ant-design_icons_es_index_js.2705f295feda25cd0649.js
amphi/pipeline-scheduler/static/vendors-node_modules_ant-design_icons_es_index_js.2705f295feda25cd0649.js.map
amphi/pipeline-scheduler/static/vendors-node_modules_antd-style_es_index_js.c55850383008d77ce320.js
amphi/pipeline-scheduler/static/vendors-node_modules_antd-style_es_index_js.c55850383008d77ce320.js.map
amphi/pipeline-scheduler/static/vendors-node_modules_antd_es_index_js.54d74831dbda53208d3a.js
amphi_scheduler-0.9.2.dist-info/METADATA
amphi_scheduler-0.9.2.dist-info/WHEEL
amphi_scheduler-0.9.2.dist-info/licenses/LICENSE
amphi_scheduler-0.9.2.dist-info/RECORD
