Metadata-Version: 2.4
Name: amphi-scheduler
Version: 0.9.2
Summary: Amphi Scheduler (JupyterLab extension + Python backend)
Project-URL: Homepage, https://amphi.ai
Project-URL: Issues, https://github.com/amphi-ai/jupyterlab-amphi/issues
Project-URL: Repository, https://github.com/amphi-ai/jupyterlab-amphi.git
Author-email: Thibaut Gourdel <tgourdel@amphi.ai>
License: Elastic License 2.0 \(ELv2\)
License-File: LICENSE
Requires-Python: >=3.8
Requires-Dist: apscheduler
Requires-Dist: jupyterlab<5,>=4
Requires-Dist: sqlalchemy
